ipywebrtc/__init__.py
ipywebrtc/_version.py
ipywebrtc/webrtc.py
ipywebrtc-0.6.0.data/data/etc/jupyter/nbconfig/notebook.d/jupyter-webrtc.json
ipywebrtc-0.6.0.data/data/share/jupyter/labextensions/jupyter-webrtc/package.json
ipywebrtc-0.6.0.data/data/share/jupyter/labextensions/jupyter-webrtc/static/138.4e7556c3ae9d9ae24107.js
ipywebrtc-0.6.0.data/data/share/jupyter/labextensions/jupyter-webrtc/static/144.58bb6060b0343f45fa1e.js
ipywebrtc-0.6.0.data/data/share/jupyter/labextensions/jupyter-webrtc/static/181.68265814113d760563ef.js
ipywebrtc-0.6.0.data/data/share/jupyter/labextensions/jupyter-webrtc/static/539.144b1c0f314578171b5d.js
ipywebrtc-0.6.0.data/data/share/jupyter/labextensions/jupyter-webrtc/static/575.2ecfd52d4241de7d67ed.js
ipywebrtc-0.6.0.data/data/share/jupyter/labextensions/jupyter-webrtc/static/575.2ecfd52d4241de7d67ed.js.LICENSE.txt
ipywebrtc-0.6.0.data/data/share/jupyter/labextensions/jupyter-webrtc/static/580.7f0228c999c95b0da346.js
ipywebrtc-0.6.0.data/data/share/jupyter/labextensions/jupyter-webrtc/static/616.c12215629a3e518b01d8.js
ipywebrtc-0.6.0.data/data/share/jupyter/labextensions/jupyter-webrtc/static/616.c12215629a3e518b01d8.js.LICENSE.txt
ipywebrtc-0.6.0.data/data/share/jupyter/labextensions/jupyter-webrtc/static/753.de91613ab3d2b3f79a3d.js
ipywebrtc-0.6.0.data/data/share/jupyter/labextensions/jupyter-webrtc/static/764.01b9abdc5df6020dcdd4.js
ipywebrtc-0.6.0.data/data/share/jupyter/labextensions/jupyter-webrtc/static/764.01b9abdc5df6020dcdd4.js.LICENSE.txt
ipywebrtc-0.6.0.data/data/share/jupyter/labextensions/jupyter-webrtc/static/826.01a996393d4a83f9b1df.js
ipywebrtc-0.6.0.data/data/share/jupyter/labextensions/jupyter-webrtc/static/908.0bb74ba42b7e6a3df846.js
ipywebrtc-0.6.0.data/data/share/jupyter/labextensions/jupyter-webrtc/static/963.248a1aaf66b442da6259.js
ipywebrtc-0.6.0.data/data/share/jupyter/labextensions/jupyter-webrtc/static/remoteEntry.a8997ccec61b65e8a4e7.js
ipywebrtc-0.6.0.dist-info/LICENSE
ipywebrtc-0.6.0.dist-info/METADATA
ipywebrtc-0.6.0.dist-info/WHEEL
ipywebrtc-0.6.0.dist-info/top_level.txt
ipywebrtc-0.6.0.dist-info/RECORD
