Metadata-Version: 1.1
Name: ipywebrtc
Version: 0.6.0
Summary: WebRTC for Jupyter notebook/lab
Home-page: https://github.com/maartenbreddels/ipywebrtc
Author: Maarten Breddels
Author-email: maartenbreddels@gmail.com
License: MIT
Keywords: ipython,jupyter,widgets
Platform: UNKNOWN
Classifier: Development Status :: 4 - Beta
Classifier: Framework :: IPython
Classifier: Intended Audience :: Developers
Classifier: Intended Audience :: Science/Research
Classifier: Topic :: Multimedia :: Graphics
Classifier: Programming Language :: Python :: 2
Classifier: Programming Language :: Python :: 2.7
Classifier: Programming Language :: Python :: 3
Classifier: Programming Language :: Python :: 3.3
Classifier: Programming Language :: Python :: 3.4
Classifier: Programming Language :: Python :: 3.5
